{
	"credit": "Model by MrCrayfish (https://twitter.com/MrCraayfish) using Blockbench",
	"textures": {
		"1": "cgm:items/weighted_stock"
	},
	"elements": [
		{
			"name": "Barrel",
			"from": [7.5, 7.5, 8],
			"to": [8.5, 8.5, 9.75],
			"rotation": {"angle": -45, "axis": "z", "origin": [8, 8, 8.75]},
			"faces": {
				"north": {"uv": [10, 14, 12, 16], "texture": "#1"},
				"east": {"uv": [12, 16, 15.5, 14], "rotation": 180, "texture": "#1"},
				"west": {"uv": [12, 16, 15.5, 14], "texture": "#1"},
				"up": {"uv": [12, 14, 15.5, 16], "rotation": 90, "texture": "#1"},
				"down": {"uv": [12, 14, 15.5, 16], "rotation": 270, "texture": "#1"}
			}
		},
		{
			"name": "Left Body",
			"from": [7.5, 6.75, 9.75],
			"to": [8.25, 7.5, 13.25],
			"rotation": {"angle": -45, "axis": "z", "origin": [8, 8, 10.5]},
			"faces": {
				"north": {"uv": [7, 2, 9, 4], "rotation": 270, "texture": "#1"},
				"south": {"uv": [7, 2, 9, 4], "rotation": 180, "texture": "#1"},
				"west": {"uv": [0, 2, 7, 3.5], "texture": "#1"}
			}
		},
		{
			"name": "Center Body",
			"from": [7.5, 7.5, 9.75],
			"to": [8.5, 8.5, 13.25],
			"rotation": {"angle": -45, "axis": "z", "origin": [8, 8, 10.5]},
			"faces": {
				"west": {"uv": [0, 0, 7, 2], "texture": "#1"},
				"up": {"uv": [7, 0, 0, 2], "rotation": 270, "texture": "#1"}
			}
		},
		{
			"name": "Right Body",
			"from": [8.5, 7.75, 9.75],
			"to": [9.25, 8.5, 13.25],
			"rotation": {"angle": -45, "axis": "z", "origin": [8, 8, 10.5]},
			"faces": {
				"north": {"uv": [7, 2, 9, 4], "rotation": 270, "texture": "#1"},
				"south": {"uv": [7, 2, 9, 4], "rotation": 180, "texture": "#1"},
				"up": {"uv": [0, 3.5, 7, 2], "rotation": 90, "texture": "#1"}
			}
		},
		{
			"name": "Bottom Body",
			"from": [6.76, 6.995, 9.75],
			"to": [9.235, 7.47, 13.25],
			"rotation": {"angle": 0, "axis": "y", "origin": [8, 7.425, 8]},
			"faces": {
				"north": {"uv": [0, 3, 1, 4], "texture": "#1"},
				"east": {"uv": [7, 3, 0, 4], "texture": "#1"},
				"south": {"uv": [8, 3, 9, 4], "texture": "#1"},
				"west": {"uv": [0, 3, 7, 4], "texture": "#1"},
				"down": {"uv": [0, 4, 7, 9], "rotation": 270, "texture": "#1"}
			}
		},
		{
			"name": "Top Butt",
			"from": [7.5, 7.5, 13.25],
			"to": [8.5, 8.5, 13.75],
			"rotation": {"angle": -45, "axis": "z", "origin": [8, 8, 13]},
			"faces": {
				"south": {"uv": [7, 2, 9, 4], "rotation": 180, "texture": "#1"},
				"west": {"uv": [7, 0, 8, 2], "texture": "#1"},
				"up": {"uv": [7, 0, 8, 2], "rotation": 270, "texture": "#1"}
			}
		},
		{
			"name": "Butt",
			"from": [7.3, 5.5, 13.2475],
			"to": [8.7, 8, 13.7525],
			"rotation": {"angle": 0, "axis": "y", "origin": [8, 7.5, 8.5]},
			"faces": {
				"north": {"uv": [14, 0, 16, 5], "rotation": 180, "texture": "#1"},
				"east": {"uv": [10, 0, 11, 5], "texture": "#1"},
				"south": {"uv": [11, 0, 13, 5], "texture": "#1"},
				"west": {"uv": [13, 0, 14, 5], "texture": "#1"}
			}
		},
		{
			"name": "Bottom Butt",
			"from": [7.5, 5, 13.25],
			"to": [8.5, 6, 13.75],
			"rotation": {"angle": 45, "axis": "z", "origin": [8, 5.5, 13.5]},
			"faces": {
				"north": {"uv": [7, 2, 9, 4], "texture": "#1"},
				"south": {"uv": [7, 2, 9, 4], "rotation": 90, "texture": "#1"},
				"west": {"uv": [7, 0, 8, 2], "rotation": 180, "texture": "#1"},
				"down": {"uv": [7, 0, 8, 2], "rotation": 270, "texture": "#1"}
			}
		},
		{
			"name": "Top Body",
			"from": [7.5, 6.5, 10.25],
			"to": [8.5, 6.75, 11],
			"rotation": {"angle": 0, "axis": "y", "origin": [8, 6.475, 10.25]},
			"faces": {
				"east": {"uv": [10, 6, 12, 7], "rotation": 180, "texture": "#1"},
				"west": {"uv": [10, 6, 12, 7], "texture": "#1"},
				"up": {"uv": [10, 6, 12, 7], "rotation": 270, "texture": "#1"},
				"down": {"uv": [10, 6, 12, 7], "rotation": 270, "texture": "#1"}
			}
		},
		{
			"name": "Bottom Body",
			"from": [7.5, 6, 11.25],
			"to": [8.5, 6.25, 11.5],
			"rotation": {"angle": 0, "axis": "y", "origin": [8, 5.955, 9.75]},
			"faces": {
				"north": {"uv": [9, 6, 10, 7], "rotation": 180, "texture": "#1"},
				"east": {"uv": [9, 6, 10, 7], "rotation": 180, "texture": "#1"},
				"south": {"uv": [9, 6, 10, 7], "rotation": 180, "texture": "#1"},
				"west": {"uv": [9, 6, 10, 7], "texture": "#1"},
				"up": {"uv": [9, 6, 10, 7], "rotation": 180, "texture": "#1"},
				"down": {"uv": [9, 6, 10, 7], "rotation": 180, "texture": "#1"}
			}
		},
		{
			"name": "Top Curve",
			"from": [7.501, 6.5, 10.25],
			"to": [8.499, 7.21, 10.6],
			"rotation": {"angle": -45, "axis": "x", "origin": [8, 6.5, 10.25]},
			"faces": {
				"north": {"uv": [9, 6, 10, 7], "texture": "#1"},
				"east": {"uv": [9, 6, 10, 7], "texture": "#1"},
				"south": {"uv": [9, 6, 10, 7], "texture": "#1"},
				"west": {"uv": [9, 6, 10, 7], "texture": "#1"}
			}
		},
		{
			"name": "Bottom Curve",
			"from": [7.501, 6, 11.25],
			"to": [8.499, 6.71, 11.6],
			"rotation": {"angle": -45, "axis": "x", "origin": [8, 6, 11.25]},
			"faces": {
				"north": {"uv": [9, 6, 10, 7], "texture": "#1"},
				"east": {"uv": [9, 6, 10, 7], "texture": "#1"},
				"south": {"uv": [9, 6, 10, 7], "texture": "#1"},
				"west": {"uv": [9, 6, 10, 7], "texture": "#1"}
			}
		},
		{
			"name": "Body",
			"from": [7.75, 6.5, 10.25],
			"to": [8.25, 7, 13.25],
			"rotation": {"angle": 0, "axis": "y", "origin": [8, 6.475, 10.25]},
			"faces": {
				"east": {"uv": [10, 6, 16, 7], "rotation": 180, "texture": "#1"},
				"west": {"uv": [10, 6, 16, 7], "texture": "#1"},
				"down": {"uv": [11, 6, 16, 7], "rotation": 270, "texture": "#1"}
			}
		},
		{
			"name": "Bottom Curve",
			"from": [7.7501, 6.365, 11.175],
			"to": [8.2481, 6.765, 13.225],
			"rotation": {"angle": 45, "axis": "x", "origin": [8, 6.35, 11.375]},
			"faces": {
				"east": {"uv": [9, 6, 10, 7], "texture": "#1"},
				"west": {"uv": [9, 6, 10, 7], "texture": "#1"},
				"down": {"uv": [9, 6, 10, 7], "texture": "#1"}
			}
		},
		{
			"name": "Top Mask",
			"from": [7.75, 6, 11.75],
			"to": [8.25, 6.5, 13.25],
			"rotation": {"angle": 0, "axis": "y", "origin": [8, 5.955, 10.25]},
			"faces": {
				"east": {"uv": [13, 7, 16, 8], "rotation": 180, "texture": "#1"},
				"west": {"uv": [13, 7, 16, 8], "texture": "#1"}
			}
		},
		{
			"name": "Center Mask",
			"from": [7.75, 5.5, 12.25],
			"to": [8.25, 6, 13.25],
			"rotation": {"angle": 0, "axis": "y", "origin": [8, 5.455, 10.25]},
			"faces": {
				"east": {"uv": [14, 8, 16, 9], "rotation": 180, "texture": "#1"},
				"west": {"uv": [14, 8, 16, 9], "texture": "#1"}
			}
		},
		{
			"name": "Bottom Mask",
			"from": [7.75, 5.055, 12.695],
			"to": [8.25, 5.5, 13.25],
			"rotation": {"angle": 0, "axis": "y", "origin": [8, 4.955, 10.25]},
			"faces": {
				"east": {"uv": [15, 9, 16, 10], "texture": "#1"},
				"west": {"uv": [15, 9, 16, 10], "texture": "#1"},
				"down": {"uv": [15, 9, 16, 10], "texture": "#1"}
			}
		}
	],
	"display": {
		"thirdperson_righthand": {
			"translation": [0, 1.25, -4.5],
			"scale": [1.1, 1.1, 1.1]
		},
		"thirdperson_lefthand": {
			"translation": [0, 1.25, -4.5],
			"scale": [1.1, 1.1, 1.1]
		},
		"firstperson_righthand": {
			"translation": [-3.5, 5.5, 3.25],
			"scale": [0.8, 0.8, 0.8]
		},
		"firstperson_lefthand": {
			"translation": [-3.5, 5.5, 3.25],
			"scale": [0.8, 0.8, 0.8]
		},
		"ground": {
			"translation": [0, -0.5, -2.25]
		},
		"gui": {
			"rotation": [30, 225, 0],
			"translation": [5.25, -1.5, 0],
			"scale": [2.5, 2.5, 2.5]
		},
		"fixed": {
			"rotation": [0, 90, 0],
			"translation": [-5.75, 1.25, -1.25],
			"scale": [2, 2, 2]
		}
	},
	"groups": [
		{
			"name": "Heavy Carbine Stock",
			"origin": [8, 6.325, 11.5],
			"color": 0,
			"children": [
				0,
				{
					"name": "Body",
					"origin": [8, 7.475, 8.25],
					"color": 0,
					"children": [1, 2, 3, 4]
				},
				{
					"name": "Butt",
					"origin": [8, 5.5, 13.75],
					"color": 0,
					"children": [5, 6, 7]
				},
				{
					"name": "Detail",
					"origin": [8, 6.325, 11.5],
					"color": 0,
					"children": [
						{
							"name": "Small Part",
							"origin": [8, 6, 11.25],
							"color": 0,
							"children": [8, 9, 10, 11]
						},
						12,
						13,
						14,
						15,
						16
					]
				}
			]
		}
	]
}